docs/conf.py
ffy00/packaging.py
tests/test_check_dependency.py
ffy00.packaging-0.1.0.dist-info/LICENSE
ffy00.packaging-0.1.0.dist-info/METADATA
ffy00.packaging-0.1.0.dist-info/WHEEL
ffy00.packaging-0.1.0.dist-info/top_level.txt
ffy00.packaging-0.1.0.dist-info/RECORD
