Metadata-Version: 2.1
Name: ffy00.packaging
Version: 0.1.0
Summary: Collection of packaging related utilities
Author-email: Filipe Laíns <lains@riseup.net>
License: Copyright © 2019 Filipe Laíns <filipe.lains@gmail.com>
Project-URL: homepage, https://github.com/FFY00/ffy00.packaging
Project-URL: changelog, https://pypa-build.readthedocs.io/en/stable/changelog.html
Classifier: License :: OSI Approved :: MIT License
Classifier: Programming Language :: Python :: 3
Classifier: Programming Language :: Python :: 3 :: Only
Classifier: Programming Language :: Python :: 3.7
Classifier: Programming Language :: Python :: 3.8
Classifier: Programming Language :: Python :: 3.9
Classifier: Programming Language :: Python :: 3.10
Classifier: Programming Language :: Python :: 3.11
Requires-Python: >=3.7
License-File: LICENSE
Requires-Dist: packaging (>=19.0)
Requires-Dist: tomli (>=1.1.0) ; python_version < "3.11"
Requires-Dist: importlib-metadata (>=0.22) ; python_version < "3.8"
Provides-Extra: docs
Requires-Dist: furo (>=2021.08.31) ; extra == 'docs'
Requires-Dist: sphinx (~=4.0) ; extra == 'docs'
Requires-Dist: sphinx-autodoc-typehints (>=1.10) ; extra == 'docs'
Requires-Dist: sphinx-copybutton (>=0.5.0) ; extra == 'docs'
Requires-Dist: sphinx-design (>=0.1.0) ; extra == 'docs'
Requires-Dist: sphinx-autobuild ; extra == 'docs'
Requires-Dist: sphinx-issues (>=3.0.0) ; extra == 'docs'
Requires-Dist: sphinxcontrib-spelling (>=7.0.0) ; extra == 'docs'
Requires-Dist: sphinxext-opengraph (>=0.7.0) ; extra == 'docs'
Provides-Extra: test
Requires-Dist: pytest (>=6.2.4) ; extra == 'test'
Requires-Dist: pytest-cov (>=2.12) ; extra == 'test'
Requires-Dist: pytest-mock (>=2) ; extra == 'test'
Provides-Extra: typing
Requires-Dist: importlib-metadata (>=5.1) ; extra == 'typing'
Requires-Dist: mypy (==0.991) ; extra == 'typing'
